cbchelpers/__init__.py
cbchelpers/_version.py
cbchelpers/cbchelpers.py
cbchelpers/colors.py
cbchelpers/cond_helpers.py
cbchelpers/derivative.py
cbchelpers/helpers.py
cbchelpers/parmed_extension.py
cbchelpers/plot_helpers.py
cbchelpers/py.typed
cbchelpers/tests/__init__.py
cbchelpers/tests/test_cbchelpers.py
cbchelpers/tests/test_parmed_extension.py
cbchelpers-0.0.3.dist-info/LICENSE
cbchelpers-0.0.3.dist-info/METADATA
cbchelpers-0.0.3.dist-info/WHEEL
cbchelpers-0.0.3.dist-info/top_level.txt
cbchelpers-0.0.3.dist-info/RECORD
