Metadata-Version: 2.1
Name: cbchelpers
Version: 0.0.3
Summary: Various functions and methods to facilitate my work
Author: Florian Joerg
Author-email: Florian Joerg <florian.joerg@univie.ac.at>
License: MIT
Classifier: License :: OSI Approved :: MIT License
Classifier: Programming Language :: Python :: 3
Requires-Python: >=3.8
License-File: LICENSE
Requires-Dist: numpy
Requires-Dist: matplotlib
Requires-Dist: scipy
Provides-Extra: test
Requires-Dist: pytest >=6.1.2 ; extra == 'test'
Requires-Dist: pytest-runner ; extra == 'test'
